SecretPlots/__init__.py
Biology-0.0.1.dist-info/LICENSE
Biology-0.0.1.dist-info/METADATA
Biology-0.0.1.dist-info/WHEEL
Biology-0.0.1.dist-info/top_level.txt
Biology-0.0.1.dist-info/RECORD
